slimDNS/__init__.py
slimDNS-1.0.0rc2.dist-info/METADATA
slimDNS-1.0.0rc2.dist-info/WHEEL
slimDNS-1.0.0rc2.dist-info/top_level.txt
slimDNS-1.0.0rc2.dist-info/RECORD
