Metadata-Version: 2.1
Name: slimDNS
Version: 1.0.0rc2
Summary: A simple DNS server written in vanilla Python.
Home-page: https://github.com/Torxed/slimDNS
Author: Anton Hvornum
Author-email: anton@hvornum.se
License: UNKNOWN
Platform: UNKNOWN
Classifier: Programming Language :: Python :: 3.8
Classifier: License :: OSI Approved :: GNU General Public License v3 (GPLv3)
Classifier: Operating System :: POSIX :: Linux
Requires-Python: >=3.8
